[
  {
    "question": "¿Qué es una herida de la piel?",
    "options": [
      {"text": "Lesión traumática con solución de continuidad de los tegumentos", "isCorrect": true, "rationale": "Una herida es una lesión traumática de la piel con solución de continuidad."},
      {"text": "Una infección bacteriana", "isCorrect": false, "rationale": "No es necesariamente infecciosa; es una lesión física."},
      {"text": "Una mancha de nacimiento", "isCorrect": false, "rationale": "No es congénita; es traumática."},
      {"text": "Una glándula inflamada", "isCorrect": false, "rationale": "No es una glándula; es una lesión del tejido."}
    ],
    "hint": "Es cuando la piel se rompe por algún trauma..."
  },
  {
    "question": "¿Qué es una herida incisa o cortante?",
    "options": [
      {"text": "Producida por instrumento con filo como cuchillo o navaja", "isCorrect": true, "rationale": "La herida incisa es producida por un instrumento con filo (cuchillo, navaja)."},
      {"text": "Producida por un golpe contuso", "isCorrect": false, "rationale": "Eso es una herida contusa."},
      {"text": "Causada por una quemadura", "isCorrect": false, "rationale": "Las quemaduras son otro tipo de lesión."},
      {"text": "Por mordedura de animal", "isCorrect": false, "rationale": "Aunque corta, se clasifica de forma diferente."}
    ],
    "hint": "Tiene bordes limpios y es causada por algo afilado..."
  },
  {
    "question": "¿Qué es una herida punzante?",
    "options": [
      {"text": "Producida por elemento con punta aguda como puñal o aguja", "isCorrect": true, "rationale": "La herida punzante es producida por un elemento con punta aguda (puñal, aguja, punzón)."},
      {"text": "Causada por un martillo", "isCorrect": false, "rationale": "Eso es contusa."},
      {"text": "Por fricción con el suelo", "isCorrect": false, "rationale": "Esa sería excoriación o abrasión."},
      {"text": "Por cuchillo", "isCorrect": false, "rationale": "El cuchillo produce herida incisa, no punzante principalmente."}
    ],
    "hint": "Es profunda y estrecha, hecha por algo puntiagudo..."
  },
  {
    "question": "¿Qué es una herida contusa?",
    "options": [
      {"text": "Producida por golpe de elemento romo como martillo", "isCorrect": true, "rationale": "La herida contusa es producida por el golpe de un elemento romo (martillo, maza)."},
      {"text": "Causada por un corte limpio", "isCorrect": false, "rationale": "Eso es incisa."},
      {"text": "Por una aguja", "isCorrect": false, "rationale": "Eso es punzante."},
      {"text": "Por radiación solar", "isCorrect": false, "rationale": "Eso es quemadura."}
    ],
    "hint": "Presenta equimosis (morados) por daño vascular..."
  },
  {
    "question": "¿Qué es una herida desgarrante?",
    "options": [
      {"text": "Lesión que separa tegumentos de forma anfractuosa", "isCorrect": true, "rationale": "La herida desgarrante separa los tegumentos de forma anfractuosa o irregular."},
      {"text": "Corte limpio y recto", "isCorrect": false, "rationale": "Los bordes son irregulares, no limpios."},
      {"text": "Herida pequeña y puntiforme", "isCorrect": false, "rationale": "Suele ser más extensa."},
      {"text": "Sin sangrado", "isCorrect": false, "rationale": "Suelen sangrar por el desgarro vascular."}
    ],
    "hint": "Los bordes son irregulares y desgarrados..."
  },
  {
    "question": "¿Qué es la cicatrización por primera intención?",
    "options": [
      {"text": "Curación con aproximación de bordes por sutura o adhesivos", "isCorrect": true, "rationale": "La cicatrización por primera intención ocurre cuando se logra la aproximación de bordes mediante sutura o adhesivos."},
      {"text": "Curación sin unir los bordes", "isCorrect": false, "rationale": "Eso es segunda intención."},
      {"text": "Formación de cicatriz queloide", "isCorrect": false, "rationale": "No es la definición de primera intención."},
      {"text": "Infección de la herida", "isCorrect": false, "rationale": "La infección complica la cicatrización."}
    ],
    "hint": "Cuando los bordes de la herida se unen quirúrgicamente..."
  },
  {
    "question": "¿Qué es la cicatrización por segunda intención?",
    "options": [
      {"text": "Curación sin que se haya logrado la aposición de bordes", "isCorrect": true, "rationale": "La segunda intención es cuando la herida cura sin aposición previa de sus bordes."},
      {"text": "Curación con suturas", "isCorrect": false, "rationale": "Eso es primera intención."},
      {"text": "Formación de cicatriz plana", "isCorrect": false, "rationale": "Las cicatrices de segunda intención suelen ser más grandes."},
      {"text": "Ausencia de cicatriz", "isCorrect": false, "rationale": "Siempre hay cicatrización, aunque sea diferente."}
    ],
    "hint": "Cuando la herida secura dejada abierta, sin unir los bordes..."
  },
  {
    "question": "¿Qué son las estrías cutáneas?",
    "options": [
      {"text": "Lesiones por ruptura de fibras elásticas por estiramiento excesivo", "isCorrect": true, "rationale": "Las estrías se producen por ruptura de fibras elásticas como consecuencia del estiramiento excesivo."},
      {"text": "Infecciones de la piel", "isCorrect": false, "rationale": "No son infecciosas."},
      {"text": "Cicatrices quirúrgicas", "isCorrect": false, "rationale": "Son por estramiento, no por corte."},
      {"text": "Manchas de nacimiento", "isCorrect": false, "rationale": "Son adquiridas, no congénitas."}
    ],
    "hint": "Aparecen en el abdomen, muslos, mamas por estiramiento...",
    "image": "imagen:estrias-cutaneas-evolucion-colores"
  },
  {
    "question": "¿Cuál es la evolución cromática de las estrías?",
    "options": [
      {"text": "Rosadas → púrpuras → blancas", "isCorrect": true, "rationale": "Las estrías evolucionan de rosadas (inicial) a púrpuras y finalmente blancas."},
      {"text": "Blancas → rojas → negras", "isCorrect": false, "rationale": "El orden de colores es incorrecto."},
      {"text": "Azules → verdes → amarillas", "isCorrect": false, "rationale": "No corresponde a la evolución de las estrías."},
      {"text": "Negras → grises → blancas", "isCorrect": false, "rationale": "No es la secuencia correcta."}
    ],
    "hint": "Inicialmente son inflamatorias (rosas), luego maduran (blancas)..."
  },
  {
    "question": "¿Qué es una quemadura?",
    "options": [
      {"text": "Lesión producida por agentes físicos, químicos o biológicos en tejidos vivos", "isCorrect": true, "rationale": "La quemadura es lesión producida en tejidos vivos por agentes físicos, químicos o biológicos."},
      {"text": "Una infección viral", "isCorrect": false, "rationale": "No es infecciosa por definición."},
      {"text": "Una reacción alérgica", "isCorrect": false, "rationale": "Aunque puede haber eritema, no es alérgica."},
      {"text": "Una mancha de pigmento", "isCorrect": false, "rationale": "Es una lesión de destrucción tisular, no solo mancha."}
    ],
    "hint": "Causa daño por calor, productos químicos, electricidad o radiación..."
  },
  {
    "question": "¿Cuánto representa el 1% de la superficie corporal según la regla de los 9?",
    "options": [
      {"text": "La región perineal", "isCorrect": true, "rationale": "La región perineal representa el 1% de la superficie corporal según la regla de los 9."},
      {"text": "La cabeza", "isCorrect": false, "rationale": "La cabeza es 9%."},
      {"text": "Un brazo", "isCorrect": false, "rationale": "Cada brazo es 9%."},
      {"text": "El tronco anterior", "isCorrect": false, "rationale": "El tronco anterior es 18%."}
    ],
    "hint": "La zona más pequeña medida por esta regla es el periné..."
  },
  {
    "question": "¿Cuánto representa cada miembro superior según la regla de los 9?",
    "options": [
      {"text": "9%", "isCorrect": true, "rationale": "Cada miembro superior representa el 9% de la superficie corporal."},
      {"text": "18%", "isCorrect": false, "rationale": "El tronco anterior o posterior es 18%."},
      {"text": "4.5%", "isCorrect": false, "rationale": "No es el valor correcto."},
      {"text": "1%", "isCorrect": false, "rationale": "El 1% es la región perineal."}
    ],
    "hint": "Cada brazo completo (frente y dorso) es 9%...",
    "image": "imagen:regla-nueve-superficie-quemaduras"
  },
  {
    "question": "¿Qué es la mamá desde el punto de vista tegumentario?",
    "options": [
      {"text": "Formación tegumentaria derivada de glándulas sudoríparas apocrinas", "isCorrect": true, "rationale": "La mama es formación tegumentaria cuyo tejido glandular se forma a partir de glándulas sudoríparas apocrinas modificadas."},
      {"text": "Un órgano muscular", "isCorrect": false, "rationale": "No es principalmente muscular."},
      {"text": "Un hueso del tórax", "isCorrect": false, "rationale": "No es ósea."},
      {"text": "Una glándula endocrina pura", "isCorrect": false, "rationale": "Es exocrina (secreta leche), no endocrina."}
    ],
    "hint": "Es una glándula exocrina modificada, parte del sistema tegumentario..."}
]